README.md
setup.cfg
setup.py
delivery/__init__.py
delivery/default.py
delivery/mac.py
delivery/utils.py
delivery.egg-info/PKG-INFO
delivery.egg-info/SOURCES.txt
delivery.egg-info/dependency_links.txt
delivery.egg-info/top_level.txt
test/test.py