Metadata-Version: 1.1
Name: delivery
Version: 0.0.1
Summary: Simple, multiplatform interface for desktop notifications
Home-page: https://github.com/jcaw/delivery/
Author: Jcaw
Author-email: toastedjcaw@gmail.com
License: MIT
Project-URL: Bug Tracker, https://github.com/jcaw/delivery/issues
Project-URL: Documentation, https://github.com/jcaw/delivery/README.md
Project-URL: Source Code, https://github.com/jcaw/delivery/
Keywords: notify,notification,notifications,desktop,toast,win10toast,plyer,terminal-notify
Platform: UNKNOWN
Classifier: Development Status :: 3 - Alpha
Classifier: Intended Audience :: Developers
Classifier: Topic :: Desktop Environment
Classifier: Topic :: Utilities
Classifier: Programming Language :: Python
Classifier: Natural Language :: English
Classifier: License :: OSI Approved :: MIT License
Classifier: Operating System :: OS Independent
Classifier: Programming Language :: Python :: 2.7
Classifier: Programming Language :: Python :: 3
